verifiers/AGENTS.md
verifiers/__init__.py
verifiers/decorators.py
verifiers/errors.py
verifiers/types.py
verifiers/envs/AGENTS.md
verifiers/envs/__init__.py
verifiers/envs/env_group.py
verifiers/envs/environment.py
verifiers/envs/multiturn_env.py
verifiers/envs/python_env.py
verifiers/envs/sandbox_env.py
verifiers/envs/singleturn_env.py
verifiers/envs/stateful_tool_env.py
verifiers/envs/tool_env.py
verifiers/envs/experimental/README.md
verifiers/envs/experimental/__init__.py
verifiers/envs/experimental/cli_agent_env.py
verifiers/envs/experimental/gym_env.py
verifiers/envs/experimental/harbor_env.py
verifiers/envs/experimental/mcp_env.py
verifiers/envs/experimental/rlm_env.py
verifiers/envs/integrations/README.md
verifiers/envs/integrations/__init__.py
verifiers/envs/integrations/reasoninggym_env.py
verifiers/envs/integrations/textarena_env.py
verifiers/parsers/__init__.py
verifiers/parsers/maybe_think_parser.py
verifiers/parsers/parser.py
verifiers/parsers/think_parser.py
verifiers/parsers/xml_parser.py
verifiers/rl/README.md
verifiers/rl/inference/__init__.py
verifiers/rl/inference/client.py
verifiers/rl/inference/server.py
verifiers/rl/trainer/__init__.py
verifiers/rl/trainer/config.py
verifiers/rl/trainer/orchestrator.py
verifiers/rl/trainer/trainer.py
verifiers/rl/trainer/utils.py
verifiers/rubrics/__init__.py
verifiers/rubrics/judge_rubric.py
verifiers/rubrics/math_rubric.py
verifiers/rubrics/rubric.py
verifiers/rubrics/rubric_group.py
verifiers/scripts/__init__.py
verifiers/scripts/eval.py
verifiers/scripts/init.py
verifiers/scripts/install.py
verifiers/scripts/prime_rl.py
verifiers/scripts/rl.py
verifiers/scripts/setup.py
verifiers/scripts/train.py
verifiers/scripts/tui.py
verifiers/utils/__init__.py
verifiers/utils/async_utils.py
verifiers/utils/client_utils.py
verifiers/utils/data_utils.py
verifiers/utils/env_utils.py
verifiers/utils/error_utils.py
verifiers/utils/eval_utils.py
verifiers/utils/logging_utils.py
verifiers/utils/message_utils.py
verifiers-0.1.9.post3.dist-info/METADATA
verifiers-0.1.9.post3.dist-info/WHEEL
verifiers-0.1.9.post3.dist-info/entry_points.txt
verifiers-0.1.9.post3.dist-info/licenses/LICENSE
verifiers-0.1.9.post3.dist-info/RECORD
