Metadata-Version: 2.4
Name: verifiers
Version: 0.1.9.post3
Summary: Verifiers: Environments for LLM Reinforcement Learning
Project-URL: Homepage, https://github.com/primeintellect-ai/verifiers
Project-URL: Documentation, https://github.com/primeintellect-ai/verifiers
Project-URL: Repository, https://github.com/primeintellect-ai/verifiers.git
Project-URL: Issues, https://github.com/primeintellect-ai/verifiers/issues
Author-email: William Brown <williambrown97@gmail.com>
License-Expression: MIT
License-File: LICENSE
Keywords: agentic-rl,agents,environments,eval,grpo,harness,llm,multi-turn,reinforcement-learning,rl,rlvr,tool-use,train,verifiers
Classifier: Development Status :: 4 - Beta
Classifier: Intended Audience :: Developers
Classifier: Intended Audience :: Science/Research
Classifier: License :: OSI Approved :: MIT License
Classifier: Programming Language :: Python :: 3
Classifier: Programming Language :: Python :: 3.10
Classifier: Programming Language :: Python :: 3.11
Classifier: Programming Language :: Python :: 3.12
Classifier: Programming Language :: Python :: 3.13
Classifier: Topic :: Scientific/Engineering :: Artificial Intelligence
Classifier: Topic :: Software Development :: Libraries :: Python Modules
Requires-Python: <3.14,>=3.10
Requires-Dist: datasets>=3.0.0
Requires-Dist: jinja2>=3.1.6
Requires-Dist: math-verify>=0.8.0
Requires-Dist: mcp>=1.14.1
Requires-Dist: nest-asyncio>=1.6.0
Requires-Dist: openai-agents>=0.0.7
Requires-Dist: openai>=1.108.1
Requires-Dist: prime-sandboxes>=0.2.9
Requires-Dist: pydantic>=2.11.9
Requires-Dist: requests
Requires-Dist: rich
Requires-Dist: tenacity>=8.5.0
Requires-Dist: textual
Requires-Dist: tomli; python_version < '3.11'
Requires-Dist: typing-extensions; python_version < '3.12'
Requires-Dist: wget>=3.2
Provides-Extra: rg
Requires-Dist: reasoning-gym; extra == 'rg'
Provides-Extra: rl
Requires-Dist: accelerate>=1.4.0; extra == 'rl'
Requires-Dist: deepspeed>=0.17.6; extra == 'rl'
Requires-Dist: flash-attn>=2.8.3; extra == 'rl'
Requires-Dist: liger-kernel>=0.5.10; extra == 'rl'
Requires-Dist: peft; extra == 'rl'
Requires-Dist: requests; extra == 'rl'
Requires-Dist: torch<2.9.0,>=2.8.0; extra == 'rl'
Requires-Dist: transformers>=4.56.2; extra == 'rl'
Requires-Dist: vllm<0.11.0,>=0.10.0; extra == 'rl'
Requires-Dist: wandb; extra == 'rl'
Provides-Extra: ta
Requires-Dist: nltk; extra == 'ta'
Requires-Dist: textarena; extra == 'ta'
